Workbook

Sheet ASSUMPTIONS
B3: Employee Assumptions
B4: Current Age | C4: 30
B5: Retirement Age | C5: 60
B6: Years to retirement | C6: 30
B7: Current Annual Salary | C7: 600000
B9: Financial Assumptions
B10: Salary growth rate | C10: 0.1
B11: Discount rate | C11: 0.075
B13: Attrition & Mortality
B14: Annual Attrition Rate | C14: 0.2
B15: Mortality Table IALM | C15: 2006-2008
B17: Benefit Formula
B18: Gratutity formula | C18: (Salary/26)*15*Service
B20: Vesting Period | C20: 5
B22: Qualifying Salary | C22: =C7/12 -> 50000
B24: Regulatory Basis
B25: Accounting Standard | C25: Ind AS 19
B26: Salary Definition | C26: Last Drawn Monthly Salary

Sheet MORTALITY & ATTRITION
A2: Age | B2: Year | C2: qx | D2: px | E2: Attrition | F2: P(staying) | G2: P(in service)
A3: 30 | B3: 1 | C3: 0.001056 | D3: =1-C3 -> 0.998944 | E3: =ASSUMPTIONS!$C$14 -> 0.2 | F3: =1-E3 -> 0.8 | G3: =D3*F3 -> 0.7991552
A4: 31 | B4: 2 | C4: 0.001084 | D4: =1-C4 -> 0.998916 | E4: =ASSUMPTIONS!$C$14 -> 0.2 | F4: =1-E4 -> 0.8 | G4: =D4*F4*G3 -> 0.63863113
A5: 32 | B5: 3 | C5: 0.001119 | D5: =1-C5 -> 0.998881 | E5: =ASSUMPTIONS!$C$14 -> 0.2 | F5: =1-E5 -> 0.8 | G5: =D5*F5*G4 -> 0.5103332
A6: 33 | B6: 4 | C6: 0.001164 | D6: =1-C6 -> 0.998836 | E6: =ASSUMPTIONS!$C$14 -> 0.2 | F6: =1-E6 -> 0.8 | G6: =D6*F6*G5 -> 0.40779134
A7: 34 | B7: 5 | C7: 0.001218 | D7: =1-C7 -> 0.998782 | E7: =ASSUMPTIONS!$C$14 -> 0.2 | F7: =1-E7 -> 0.8 | G7: =D7*F7*G6 -> 0.32583572
A8: 35 | B8: 6 | C8: 0.001282 | D8: =1-C8 -> 0.998718 | E8: =ASSUMPTIONS!$C$14 -> 0.2 | F8: =1-E8 -> 0.8 | G8: =D8*F8*G7 -> 0.2603344
A9: 36 | B9: 7 | C9: 0.001358 | D9: =1-C9 -> 0.998642 | E9: =ASSUMPTIONS!$C$14 -> 0.2 | F9: =1-E9 -> 0.8 | G9: =D9*F9*G8 -> 0.20798469
A10: 37 | B10: 8 | C10: 0.001447 | D10: =1-C10 -> 0.998553 | E10: =ASSUMPTIONS!$C$14 -> 0.2 | F10: =1-E10 -> 0.8 | G10: =D10*F10*G9 -> 0.16614699
A11: 38 | B11: 9 | C11: 0.001549 | D11: =1-C11 -> 0.998451 | E11: =ASSUMPTIONS!$C$14 -> 0.2 | F11: =1-E11 -> 0.8 | G11: =D11*F11*G10 -> 0.1327117
A12: 39 | B12: 10 | C12: 0.001667 | D12: =1-C12 -> 0.998333 | E12: =ASSUMPTIONS!$C$14 -> 0.2 | F12: =1-E12 -> 0.8 | G12: =D12*F12*G11 -> 0.10599238
A13: 40 | B13: 11 | C13: 0.001803 | D13: =1-C13 -> 0.998197 | E13: =ASSUMPTIONS!$C$14 -> 0.2 | F13: =1-E13 -> 0.8 | G13: =D13*F13*G12 -> 0.084641019
A14: 41 | B14: 12 | C14: 0.001959 | D14: =1-C14 -> 0.998041 | E14: =ASSUMPTIONS!$C$14 -> 0.2 | F14: =1-E14 -> 0.8 | G14: =D14*F14*G13 -> 0.067580166
A15: 42 | B15: 13 | C15: 0.00214 | D15: =1-C15 -> 0.99786 | E15: =ASSUMPTIONS!$C$14 -> 0.2 | F15: =1-E15 -> 0.8 | G15: =D15*F15*G14 -> 0.053948435
... A33: 60 | B33: 31 | C33: 0.01149 | D33: =1-C33 -> 0.98851 | E33: =ASSUMPTIONS!$C$14 -> 0.2 | F33: =1-E33 -> 0.8 | G33: =D33*F33*G32 -> 0.00086924107

Sheet SALARY PROJECTION
A2: Age | B2: Year | C2: Annual Salary | D2: Monthly Salary | E2: Gratuity If Exit
A3: 30 | B3: 1 | C3: =ASSUMPTIONS!C7 -> 600000 | D3: =C3/12 -> 50000 | E3: =(D3/26)*15*B3 -> 28846.154
A4: 31 | B4: 2 | C4: =C3*(1+ASSUMPTIONS!$C$10) -> 660000 | D4: =C4/12 -> 55000 | E4: =(D4/26)*15*B4 -> 63461.538
A5: 32 | B5: 3 | C5: =C4*(1+ASSUMPTIONS!$C$10) -> 726000 | D5: =C5/12 -> 60500 | E5: =(D5/26)*15*B5 -> 104711.54
A6: 33 | B6: 4 | C6: =C5*(1+ASSUMPTIONS!$C$10) -> 798600 | D6: =C6/12 -> 66550 | E6: =(D6/26)*15*B6 -> 153576.92
A7: 34 | B7: 5 | C7: =C6*(1+ASSUMPTIONS!$C$10) -> 878460 | D7: =C7/12 -> 73205 | E7: =(D7/26)*15*B7 -> 211168.27
A8: 35 | B8: 6 | C8: =C7*(1+ASSUMPTIONS!$C$10) -> 966306 | D8: =C8/12 -> 80525.5 | E8: =(D8/26)*15*B8 -> 278742.12
A9: 36 | B9: 7 | C9: =C8*(1+ASSUMPTIONS!$C$10) -> 1062936.6 | D9: =C9/12 -> 88578.05 | E9: =(D9/26)*15*B9 -> 357719.05
A10: 37 | B10: 8 | C10: =C9*(1+ASSUMPTIONS!$C$10) -> 1169230.3 | D10: =C10/12 -> 97435.855 | E10: =(D10/26)*15*B10 -> 449703.95
A11: 38 | B11: 9 | C11: =C10*(1+ASSUMPTIONS!$C$10) -> 1286153.3 | D11: =C11/12 -> 107179.44 | E11: =(D11/26)*15*B11 -> 556508.63
A12: 39 | B12: 10 | C12: =C11*(1+ASSUMPTIONS!$C$10) -> 1414768.6 | D12: =C12/12 -> 117897.38 | E12: =(D12/26)*15*B12 -> 680177.22
A13: 40 | B13: 11 | C13: =C12*(1+ASSUMPTIONS!$C$10) -> 1556245.5 | D13: =C13/12 -> 129687.12 | E13: =(D13/26)*15*B13 -> 823014.43
A14: 41 | B14: 12 | C14: =C13*(1+ASSUMPTIONS!$C$10) -> 1711870 | D14: =C14/12 -> 142655.84 | E14: =(D14/26)*15*B14 -> 987617.32
A15: 42 | B15: 13 | C15: =C14*(1+ASSUMPTIONS!$C$10) -> 1883057 | D15: =C15/12 -> 156921.42 | E15: =(D15/26)*15*B15 -> 1176910.6
... A33: 60 | B33: 31 | C33: =C32*(1+ASSUMPTIONS!$C$10) -> 10469641 | D33: =C33/12 -> 872470.11 | E33: =(D33/26)*15*B33 -> 15603792

Sheet LIABILITY CALC
A2: Age | B2: Year | C2: Gratuity if Exit | D2: P(in service) | E2: Expected benefit | F2: Discount Factor | G2: Pv of Benefit
A3: 30 | B3: 1 | C3: =IF(B3<5,0,'SALARY PROJECTION'!E3) -> 0 | D3: ='MORTALITY & ATTRITION'!G3 -> 0.7991552 | E3: =C3*D3 -> 0 | F3: =1/(1+ASSUMPTIONS!$C$11)^'LIABILITY CALC'!B3 -> 0.93023256 | G3: =E3*F3 -> 0
A4: 31 | B4: 2 | C4: =IF(B4<5,0,'SALARY PROJECTION'!E4) -> 0 | D4: ='MORTALITY & ATTRITION'!G4 -> 0.63863113 | E4: =C4*D4 -> 0 | F4: =1/(1+ASSUMPTIONS!$C$11)^'LIABILITY CALC'!B4 -> 0.86533261 | G4: =E4*F4 -> 0
A5: 32 | B5: 3 | C5: =IF(B5<5,0,'SALARY PROJECTION'!E5) -> 0 | D5: ='MORTALITY & ATTRITION'!G5 -> 0.5103332 | E5: =C5*D5 -> 0 | F5: =1/(1+ASSUMPTIONS!$C$11)^'LIABILITY CALC'!B5 -> 0.80496057 | G5: =E5*F5 -> 0
A6: 33 | B6: 4 | C6: =IF(B6<5,0,'SALARY PROJECTION'!E6) -> 0 | D6: ='MORTALITY & ATTRITION'!G6 -> 0.40779134 | E6: =C6*D6 -> 0 | F6: =1/(1+ASSUMPTIONS!$C$11)^'LIABILITY CALC'!B6 -> 0.74880053 | G6: =E6*F6 -> 0
A7: 34 | B7: 5 | C7: =IF(B7<5,0,'SALARY PROJECTION'!E7) -> 211168.27 | D7: ='MORTALITY & ATTRITION'!G7 -> 0.32583572 | E7: =C7*D7 -> 68806.165 | F7: =1/(1+ASSUMPTIONS!$C$11)^'LIABILITY CALC'!B7 -> 0.69655863 | G7: =E7*F7 -> 47927.528
A8: 35 | B8: 6 | C8: =IF(B8<5,0,'SALARY PROJECTION'!E8) -> 278742.12 | D8: ='MORTALITY & ATTRITION'!G8 -> 0.2603344 | E8: =C8*D8 -> 72566.161 | F8: =1/(1+ASSUMPTIONS!$C$11)^'LIABILITY CALC'!B8 -> 0.64796152 | G8: =E8*F8 -> 47020.08
A9: 36 | B9: 7 | C9: =IF(B9<5,0,'SALARY PROJECTION'!E9) -> 357719.05 | D9: ='MORTALITY & ATTRITION'!G9 -> 0.20798469 | E9: =C9*D9 -> 74400.086 | F9: =1/(1+ASSUMPTIONS!$C$11)^'LIABILITY CALC'!B9 -> 0.6027549 | G9: =E9*F9 -> 44845.017
A10: 37 | B10: 8 | C10: =IF(B10<5,0,'SALARY PROJECTION'!E10) -> 449703.95 | D10: ='MORTALITY & ATTRITION'!G10 -> 0.16614699 | E10: =C10*D10 -> 74716.957 | F10: =1/(1+ASSUMPTIONS!$C$11)^'LIABILITY CALC'!B10 -> 0.56070223 | G10: =E10*F10 -> 41893.965
A11: 38 | B11: 9 | C11: =IF(B11<5,0,'SALARY PROJECTION'!E11) -> 556508.63 | D11: ='MORTALITY & ATTRITION'!G11 -> 0.1327117 | E11: =C11*D11 -> 73855.209 | F11: =1/(1+ASSUMPTIONS!$C$11)^'LIABILITY CALC'!B11 -> 0.52158347 | G11: =E11*F11 -> 38521.656
A12: 39 | B12: 10 | C12: =IF(B12<5,0,'SALARY PROJECTION'!E12) -> 680177.22 | D12: ='MORTALITY & ATTRITION'!G12 -> 0.10599238 | E12: =C12*D12 -> 72093.601 | F12: =1/(1+ASSUMPTIONS!$C$11)^'LIABILITY CALC'!B12 -> 0.48519393 | G12: =E12*F12 -> 34979.377
A13: 40 | B13: 11 | C13: =IF(B13<5,0,'SALARY PROJECTION'!E13) -> 823014.43 | D13: ='MORTALITY & ATTRITION'!G13 -> 0.084641019 | E13: =C13*D13 -> 69660.781 | F13: =1/(1+ASSUMPTIONS!$C$11)^'LIABILITY CALC'!B13 -> 0.45134319 | G13: =E13*F13 -> 31440.919
A14: 41 | B14: 12 | C14: =IF(B14<5,0,'SALARY PROJECTION'!E14) -> 987617.32 | D14: ='MORTALITY & ATTRITION'!G14 -> 0.067580166 | E14: =C14*D14 -> 66743.342 | F14: =1/(1+ASSUMPTIONS!$C$11)^'LIABILITY CALC'!B14 -> 0.41985413 | G14: =E14*F14 -> 28022.468
... A33: 60 | B33: 31 | C33: =IF(B33<5,0,'SALARY PROJECTION'!E33) -> 15603792 | D33: ='MORTALITY & ATTRITION'!G33 -> 0.00086924107 | E33: =C33*D33 -> 13563.457 | F33: =1/(1+ASSUMPTIONS!$C$11)^'LIABILITY CALC'!B33 -> 0.10625212 | G33: =E33*F33 -> 1441.1461
G34: =SUM(G3:G33) -> 486902.44 | H34: total pv

Sheet SENSITIVITY
B2: Discount Rate | C2: Pv of Obligation
B3: 0.05 | C3: 645490.31
B4: 0.06 | C4: 574852.49
B5: 0.07 | C5: 514101
B6: 7.5% (base) | C6: 486902.44
B7: 0.08 | C7: 461581.4
B8: 0.09 | C8: 415954.46
B9: 0.1 | C9: 376130.06
B18: Salary Growth | C18: Pv of obligation
B19: 0.06 | C19: 335845.83
B20: 0.08 | C20: 403074.08
B21: 10% (base) | C21: 486902.44
B22: 0.12 | C22: 592411.93
B23: 0.14 | C23: 726495.22
B37: Attrition | C37: Pv of Obligation
B38: 0.1 | C38: 2517910.3
B39: 0.15 | C39: 1050731.8
B40: 0.2 (base) | C40: 486902.44
B41: 0.25 | C41: 244624.43
B42: 0.3 | C42: 129498.3
